gols/__init__.py
gols/__main__.py
gols/cli.py
gols-1.2.0.dist-info/AUTHORS.rst
gols-1.2.0.dist-info/METADATA
gols-1.2.0.dist-info/WHEEL
gols-1.2.0.dist-info/entry_points.txt
gols-1.2.0.dist-info/top_level.txt
gols-1.2.0.dist-info/RECORD
