Metadata-Version: 2.1
Name: gols
Version: 1.2.0
Summary: gols
Home-page: https://github.com/euri10/gols
Author: Benoit Barthelet
Author-email: benoit.barthelet@gmail.com
License: BSD license
Platform: UNKNOWN
Classifier: Development Status :: 5 - Production/Stable
Classifier: Intended Audience :: Developers
Classifier: License :: OSI Approved :: BSD License
Classifier: Operating System :: Unix
Classifier: Operating System :: POSIX
Classifier: Programming Language :: Python
Classifier: Programming Language :: Python :: 2.7
Classifier: Programming Language :: Python :: 3
Classifier: Programming Language :: Python :: 3.3
Classifier: Programming Language :: Python :: 3.4
Classifier: Programming Language :: Python :: 3.5
Classifier: Programming Language :: Python :: 3.6
Classifier: Programming Language :: Python :: Implementation :: CPython
Classifier: Programming Language :: Python :: Implementation :: PyPy
Classifier: Topic :: Utilities
Requires-Dist: click
Requires-Dist: pytest
Requires-Dist: testfixtures
Requires-Dist: requests
Requires-Dist: beautifulsoup4
